example_publish_pypi/__init__.py
example_publish_pypi/_version.py
example_publish_pypi/main.py
example_publish_pypi-0.0.4.dist-info/METADATA
example_publish_pypi-0.0.4.dist-info/WHEEL
example_publish_pypi-0.0.4.dist-info/top_level.txt
example_publish_pypi-0.0.4.dist-info/RECORD
