Metadata-Version: 2.1
Name: example-publish-pypi
Version: 0.0.4
Summary: How to publish on PyPi
Author-email: First Second <first.second@mail.com>
License: Apache 2.0
Requires-Python: >=3.10
Requires-Dist: numpy
Provides-Extra: lint
Requires-Dist: pylint; extra == "lint"
Provides-Extra: code
Requires-Dist: black; extra == "code"
Requires-Dist: isort; extra == "code"
Provides-Extra: dev
Requires-Dist: example-publish-pypi[code,lint]; extra == "dev"
